python3email/__init__.py
python3email/python3email.py
python3email-1.16.dist-info/LICENSE.txt
python3email-1.16.dist-info/METADATA
python3email-1.16.dist-info/WHEEL
python3email-1.16.dist-info/top_level.txt
python3email-1.16.dist-info/RECORD
