Metadata-Version: 2.1
Name: python3email
Version: 1.16
Summary: string to date
Home-page: https://github.com/
Author: maisge
Author-email: 2696047693@qq.com
License: MIT
Platform: UNKNOWN
